configmerger.py
configmerger-0.2.0.dist-info/LICENSE
configmerger-0.2.0.dist-info/WHEEL
configmerger-0.2.0.dist-info/METADATA
configmerger-0.2.0.dist-info/RECORD
