Metadata-Version: 2.1
Name: configmerger
Version: 0.2.0
Summary: merge multi level configurations
Home-page: https://github.com/Cologler/configmerger-python
License: MIT
Author: Cologler
Author-email: skyoflw@gmail.com
Requires-Python: >=3.8,<4.0
Classifier: License :: OSI Approved :: MIT License
Classifier: Programming Language :: Python :: 3
Classifier: Programming Language :: Python :: 3.8
Classifier: Programming Language :: Python :: 3.9
